1_RTL/4_SEQ_LOGIC/1_LATCH/d_latch.v
`timescale 1ns/1ps

module d_latch (
    // port list
    clk         ,
    i_d         , 
    o_q
);

input   clk         ;
input   i_d         ;
output  o_q         ;

reg     o_q         ;
always @(*) begin
    if( clk ) o_q <= i_d;
end
    
endmodule

1_RTL/4_SEQ_LOGIC/1_LATCH/tb_d_latch.v
`timescale 1ns/1ps

module tb_d_latch();

    // stimulus signal
    reg     clk     ;
    reg     i_d     ;

    // monitor signal
    wire    o_q     ;


    // DUT instantiation
    d_latch DUT(
        .clk(clk),
        .i_d(i_d),
        .o_q(o_q)
    );


    // clock gen
    always #5 clk = ~clk;    // 10ns


    // put stimulus
    initial begin

        // VCD waveform dump
        $dumpfile("d_latch.vcd");
        $dumpvars(0, tb_d_latch);

        clk = 1'b0;
        i_d = 1'b0;

        #15 i_d = 1'b1;  #20 i_d = 1'b0;
        #10 i_d = 1'b1;  #10 i_d = 1'b0;
        #10 i_d = 1'b1;  #15 i_d = 1'b0;

        #50;
        $finish;

    end

endmodule

1_RTL/4_SEQ_LOGIC/1_LATCH/d_latch.vcd
$date
    Oct  2, 2026  16:46:12
$end
$version
    TOOL:	xmsim(64)	22.03-s012
$end
$timescale
    1 ps
$end

$scope module tb_d_latch $end
$var reg       1 !    clk $end
$var reg       1 "    i_d $end
$var wire      1 #    o_q  $end

$scope module DUT $end
$var wire      1 $    clk  $end
$var wire      1 %    i_d  $end
$var reg       1 &    o_q $end
$upscope $end

$upscope $end

$enddefinitions $end
$dumpvars
0!
0"
x#
0$
0%
x&
$end
#5000
1!
1$
0&
0#
#10000
0!
0$
#15000
1"
1!
1$
1%
1&
1#
#20000
0!
0$
#25000
1!
1$
#30000
0!
0$
#35000
0"
1!
1$
0%
0&
0#
#40000
0!
0$
#45000
1"
1!
1$
1%
1&
1#
#50000
0!
0$
#55000
0"
1!
1$
0%
0&
0#
#60000
0!
0$
#65000
1"
1!
1$
1%
1&
1#
#70000
0!
0$
#75000
1!
1$
#80000
0"
0!
0$
0%
#85000
1!
1$
0&
0#
