1_RTL/4_SEQ_LOGIC/4_SHIFT_REGISTER/shift_register_sipo.v
`timescale 1ns / 1ps

module shift_register_sipo #(
    parameter WIDTH = 8
)(
    // port list
    clk             ,
    rst_n           ,
    i_serial_in     ,
    o_parallel_out
);
// port declaration
input clk;
input rst_n;
input i_serial_in;
output [WIDTH-1:0] o_parallel_out;

// modeling
//reg [WIDTH-1:0] o_parallel_out;
reg [WIDTH-1:0] r_shift;
always @(posedge clk or negedge rst_n) begin
    if (~rst_n) begin
        //o_parallel_out <= 8'b0;
        r_shift <= 8'b0;
    end else begin
        //o_parallel_out <= {o_parallel_out[6:0], i_serial_in}; 
        r_shift <= {r_shift[6:0], i_serial_in};
        //r_shift[0] = i_serial_in;
        //r_shift = r_shift << 1;
    end
end

assign o_parallel_out = r_shift;

endmodule

1_RTL/4_SEQ_LOGIC/4_SHIFT_REGISTER/tb_shift_register_sipo.v
`timescale 1ns / 1ps

module tb_shift_register_sipo;
    // local parameter
    localparam WIDTH = 8;
    // stimulus signal
    reg                 clk;
    reg                 rst_n;
    reg                 i_serial_in;
    // monitor signal
    wire [WIDTH-1:0]    o_parallel_out;


    // DUT instantiation
    shift_register_sipo uut (
        .clk            (clk),
        .rst_n          (rst_n),
        .i_serial_in    (i_serial_in),
        .o_parallel_out (o_parallel_out)
    );

    // clock gen
    initial begin
        clk = 0;
        forever #5 clk = ~clk;    // 10ns (100MHz)
    end

    // Test Scenario
    initial begin
        // VCD waveform dump
        $dumpfile("shift_register_sipo.vcd");
        $dumpvars(0, tb_shift_register_sipo);
        // t=0: init
        rst_n = 1'b0; i_serial_in = 0;
        #15 rst_n = 1'b1;         // reset off = system on
        // random vector generations
        repeat(WIDTH*2) begin
            @(negedge clk);
            i_serial_in = $random % 2;
        end

        #50 $finish;
    end

    // independent monitoring block
    initial begin
        $monitor("time=%0t | reset=%b | serial_in=%b | parallel_out=%b", $time, rst_n, i_serial_in, o_parallel_out);
    end

endmodule

1_RTL/4_SEQ_LOGIC/4_SHIFT_REGISTER/shift_register_sipo.vcd
$date
    Oct  3, 2026  15:26:48
$end
$version
    TOOL:	xmsim(64)	22.03-s012
$end
$timescale
    1 ps
$end

$scope module tb_shift_register_sipo $end
$var parameter 32 !    WIDTH $end
$var reg       1 "    clk $end
$var reg       1 #    rst_n $end
$var reg       1 $    i_serial_in $end
$var wire      8 %    o_parallel_out [7:0] $end

$scope module uut $end
$var parameter 32 &    WIDTH $end
$var wire      1 '    clk  $end
$var wire      1 (    rst_n  $end
$var wire      1 )    i_serial_in  $end
$var wire      8 %    o_parallel_out [7:0] $end
$var reg       8 *    r_shift [7:0] $end
$upscope $end

$upscope $end

$enddefinitions $end
$dumpvars
b1000 &
b1000 !
0"
0#
0$
b0 %
0'
0(
0)
b0 *
$end
#5000
1"
1'
#10000
0"
0'
#15000
1#
1"
1'
1(
#20000
0"
0'
#25000
1"
1'
#30000
0"
1$
1)
0'
#35000
1"
1'
b1 *
b1 %
#40000
0"
0'
#45000
1"
1'
b11 *
b11 %
#50000
0"
0'
#55000
1"
1'
b111 *
b111 %
#60000
0"
0'
#65000
1"
1'
b1111 *
b1111 %
#70000
0"
0'
#75000
1"
1'
b11111 *
b11111 %
#80000
0"
0'
#85000
1"
1'
b111111 *
b111111 %
#90000
0"
0$
0)
0'
#95000
1"
1'
b1111110 *
b1111110 %
#100000
0"
1$
1)
0'
#105000
1"
1'
b11111101 *
b11111101 %
#110000
0"
0'
#115000
1"
1'
b11111011 *
b11111011 %
#120000
0"
0$
0)
0'
#125000
1"
1'
b11110110 *
b11110110 %
#130000
0"
1$
1)
0'
#135000
1"
1'
b11101101 *
b11101101 %
#140000
0"
0'
#145000
1"
1'
b11011011 *
b11011011 %
#150000
0"
0$
0)
0'
#155000
1"
1'
b10110110 *
b10110110 %
#160000
0"
1$
1)
0'
#165000
1"
1'
b1101101 *
b1101101 %
#170000
0"
0$
0)
0'
#175000
1"
1'
b11011010 *
b11011010 %
#180000
0"
0'
#185000
1"
1'
b10110100 *
b10110100 %
#190000
0"
0'
#195000
1"
1'
b1101000 *
b1101000 %
#200000
0"
0'
#205000
1"
1'
b11010000 *
b11010000 %
#210000
0"
0'
#215000
1"
1'
b10100000 *
b10100000 %
